yfpay/__init__.py
yfpay/client.py
yfpay/http.py
yfpay/models.py
yfpay-0.0.2.dist-info/METADATA
yfpay-0.0.2.dist-info/WHEEL
yfpay-0.0.2.dist-info/top_level.txt
yfpay-0.0.2.dist-info/RECORD
