Metadata-Version: 2.1
Name: yfpay
Version: 0.0.2
Summary: 银飞支付
Home-page: https://github.com
Author: zzz
Author-email: zzz@zzz.com
License: UNKNOWN
Project-URL: Source, https://github.com
Keywords: yinfei
Platform: UNKNOWN
Classifier: Development Status :: 5 - Production/Stable
Classifier: Intended Audience :: Developers
Classifier: Topic :: Software Development :: Build Tools
Classifier: License :: OSI Approved :: MIT License
Classifier: Programming Language :: Python :: 3.9
Classifier: Programming Language :: Python :: Implementation :: CPython
Classifier: Programming Language :: Python :: Implementation :: PyPy
Requires-Dist: pydantic
Requires-Dist: httpx
